eopf_geozarr/__init__.py
eopf_geozarr/__main__.py
eopf_geozarr/_version.py
eopf_geozarr/cli.py
eopf_geozarr/types.py
eopf_geozarr/conversion/__init__.py
eopf_geozarr/conversion/fs_utils.py
eopf_geozarr/conversion/geozarr.py
eopf_geozarr/conversion/sentinel1_reprojection.py
eopf_geozarr/conversion/utils.py
eopf_geozarr/data_api/__init__.py
eopf_geozarr/data_api/s1.py
eopf_geozarr/data_api/s2.py
eopf_geozarr/data_api/geozarr/__init__.py
eopf_geozarr/data_api/geozarr/common.py
eopf_geozarr/data_api/geozarr/geoproj.py
eopf_geozarr/data_api/geozarr/projjson.py
eopf_geozarr/data_api/geozarr/spatial.py
eopf_geozarr/data_api/geozarr/types.py
eopf_geozarr/data_api/geozarr/v2.py
eopf_geozarr/data_api/geozarr/v3.py
eopf_geozarr/data_api/geozarr/multiscales/__init__.py
eopf_geozarr/data_api/geozarr/multiscales/geozarr.py
eopf_geozarr/data_api/geozarr/multiscales/tms.py
eopf_geozarr/data_api/geozarr/multiscales/zcm.py
eopf_geozarr/pyz/__init__.py
eopf_geozarr/pyz/common.py
eopf_geozarr/pyz/v2.py
eopf_geozarr/pyz/v3.py
eopf_geozarr/s2_optimization/__init__.py
eopf_geozarr/s2_optimization/common.py
eopf_geozarr/s2_optimization/s2_band_mapping.py
eopf_geozarr/s2_optimization/s2_converter.py
eopf_geozarr/s2_optimization/s2_data_consolidator.py
eopf_geozarr/s2_optimization/s2_multiscale.py
eopf_geozarr/s2_optimization/s2_resampling.py
eopf_geozarr/s2_optimization/s2_validation.py
eopf_geozarr-0.7.1.dist-info/licenses/LICENSE
eopf_geozarr-0.7.1.dist-info/METADATA
eopf_geozarr-0.7.1.dist-info/WHEEL
eopf_geozarr-0.7.1.dist-info/entry_points.txt
eopf_geozarr-0.7.1.dist-info/top_level.txt
eopf_geozarr-0.7.1.dist-info/RECORD
