Metadata-Version: 2.4
Name: eopf-geozarr
Version: 0.7.1
Summary: GeoZarr compliant data model for EOPF datasets
Author-email: Development Seed <info@developmentseed.org>
Maintainer-email: Development Seed <info@developmentseed.org>
License: Apache-2.0
Project-URL: Homepage, https://github.com/developmentseed/eopf-geozarr
Project-URL: Repository, https://github.com/developmentseed/eopf-geozarr
Project-URL: Issues, https://github.com/developmentseed/eopf-geozarr/issues
Project-URL: Documentation, https://github.com/developmentseed/eopf-geozarr/tree/main/docs
Keywords: zarr,eopf,sentinel,geospatial,geozarr
Classifier: Development Status :: 3 - Alpha
Classifier: Intended Audience :: Science/Research
Classifier: License :: OSI Approved :: Apache Software License
Classifier: Operating System :: OS Independent
Classifier: Programming Language :: Python :: 3
Classifier: Programming Language :: Python :: 3.10
Classifier: Programming Language :: Python :: 3.11
Classifier: Programming Language :: Python :: 3.12
Classifier: Topic :: Scientific/Engineering :: GIS
Classifier: Topic :: Scientific/Engineering :: Atmospheric Science
Requires-Python: >=3.11
License-File: LICENSE
Requires-Dist: pydantic-zarr>=0.8.0
Requires-Dist: pydantic>=2.12
Requires-Dist: zarr>=3.1.1
Requires-Dist: xarray>=2025.7.1
Requires-Dist: dask[array,distributed]>=2025.5.1
Requires-Dist: numpy>=2.3.1
Requires-Dist: rioxarray>=0.13.0
Requires-Dist: cf-xarray>=0.8.0
Requires-Dist: typing-extensions>=4.15.0
Requires-Dist: aiohttp>=3.8.1
Requires-Dist: s3fs>=2024.6.0
Requires-Dist: boto3>=1.34.0
Requires-Dist: pyproj>=3.7.0
Requires-Dist: structlog>=25.5.0
Dynamic: license-file
